stmlab/__exe__.py
stmlab/__init__.py
stmlab/assets/favicon.ico
stmlab/assets/stmlab_icon.png
stmlab/assets/wallpaper.png
stmlab/command/__init__.py
stmlab/service/__init__.py
stmlab-0.14.0.dist-info/LICENSE
stmlab-0.14.0.dist-info/METADATA
stmlab-0.14.0.dist-info/WHEEL
stmlab-0.14.0.dist-info/entry_points.txt
stmlab-0.14.0.dist-info/RECORD
